flask_pages
