Metadata-Version: 1.0
Name: Flask-Pages
Version: 0.1.4
Summary: Another? flask extension that provides dynamic pages.
Home-page: https://github.com/bschumacher/Flask-Pages
Author: Bill Schumacher
Author-email: bill@servernet.co
License: LGPLv3
Keywords: flask page wysiwyg dynamic
Platform: UNKNOWN
